batool/__init__.py
batool/utils/__init__.py
batool/utils/base.py
batool/utils/fs.py
batool/utils/oss/__init__.py
batool/utils/oss/s3help.py
batool-0.1.5.dist-info/WHEEL
batool-0.1.5.dist-info/METADATA
batool-0.1.5.dist-info/RECORD
